<?xml version="1.0"?>
<rsp status_code="0" status_message="Success">
  <daily_counts>
    <count date="20080527T00:00:00">0</count>
    <count date="20080528T00:00:00">0</count>
    <count date="20080529T00:00:00">0</count>
    <count date="20080530T00:00:00">0</count>
    <count date="20080531T00:00:00">0</count>
    <count date="20080601T00:00:00">0</count>
    <count date="20080602T00:00:00">0</count>
    <count date="20080603T00:00:00">0</count>
    <count date="20080604T00:00:00">0</count>
    <count date="20080605T00:00:00">0</count>
    <count date="20080606T00:00:00">0</count>
    <count date="20080607T00:00:00">0</count>
    <count date="20080608T00:00:00">0</count>
    <count date="20080609T00:00:00">0</count>
    <count date="20080610T00:00:00">0</count>
    <count date="20080611T00:00:00">0</count>
    <count date="20080612T00:00:00">0</count>
    <count date="20080613T00:00:00">0</count>
    <count date="20080614T00:00:00">0</count>
    <count date="20080615T00:00:00">0</count>
    <count date="20080616T00:00:00">0</count>
    <count date="20080617T00:00:00">0</count>
    <count date="20080618T00:00:00">0</count>
    <count date="20080619T00:00:00">0</count>
    <count date="20080620T00:00:00">0</count>
    <count date="20080621T00:00:00">0</count>
    <count date="20080622T00:00:00">0</count>
    <count date="20080623T00:00:00">0</count>
    <count date="20080624T00:00:00">0</count>
    <count date="20080625T00:00:00">0</count>
    <count date="20080626T00:00:00">0</count>
    <count date="20080627T00:00:00">0</count>
    <count date="20080628T00:00:00">0</count>
    <count date="20080629T00:00:00">0</count>
    <count date="20080630T00:00:00">0</count>
    <count date="20080701T00:00:00">0</count>
    <count date="20080702T00:00:00">0</count>
    <count date="20080703T00:00:00">0</count>
    <count date="20080704T00:00:00">0</count>
    <count date="20080705T00:00:00">0</count>
    <count date="20080706T00:00:00">0</count>
    <count date="20080707T00:00:00">0</count>
    <count date="20080708T00:00:00">0</count>
    <count date="20080709T00:00:00">0</count>
    <count date="20080710T00:00:00">0</count>
    <count date="20080711T00:00:00">0</count>
    <count date="20080712T00:00:00">0</count>
    <count date="20080713T00:00:00">0</count>
    <count date="20080714T00:00:00">0</count>
    <count date="20080715T00:00:00">0</count>
    <count date="20080716T00:00:00">0</count>
    <count date="20080717T00:00:00">0</count>
    <count date="20080718T00:00:00">0</count>
    <count date="20080719T00:00:00">0</count>
    <count date="20080720T00:00:00">0</count>
    <count date="20080721T00:00:00">0</count>
    <count date="20080722T00:00:00">0</count>
    <count date="20080723T00:00:00">0</count>
    <count date="20080724T00:00:00">0</count>
    <count date="20080725T00:00:00">0</count>
    <count date="20080726T00:00:00">0</count>
    <count date="20080727T00:00:00">0</count>
    <count date="20080728T00:00:00">0</count>
    <count date="20080729T00:00:00">0</count>
    <count date="20080730T00:00:00">0</count>
    <count date="20080731T00:00:00">0</count>
    <count date="20080801T00:00:00">0</count>
    <count date="20080802T00:00:00">0</count>
    <count date="20080803T00:00:00">0</count>
    <count date="20080804T00:00:00">0</count>
    <count date="20080805T00:00:00">0</count>
    <count date="20080806T00:00:00">0</count>
    <count date="20080807T00:00:00">0</count>
    <count date="20080808T00:00:00">0</count>
    <count date="20080809T00:00:00">0</count>
    <count date="20080810T00:00:00">0</count>
    <count date="20080811T00:00:00">0</count>
    <count date="20080812T00:00:00">0</count>
    <count date="20080813T00:00:00">0</count>
    <count date="20080814T00:00:00">0</count>
    <count date="20080815T00:00:00">0</count>
    <count date="20080816T00:00:00">0</count>
    <count date="20080817T00:00:00">0</count>
    <count date="20080818T00:00:00">0</count>
    <count date="20080819T00:00:00">0</count>
    <count date="20080820T00:00:00">0</count>
    <count date="20080821T00:00:00">0</count>
    <count date="20080822T00:00:00">0</count>
    <count date="20080823T00:00:00">0</count>
    <count date="20080824T00:00:00">0</count>
    <count date="20080825T00:00:00">0</count>
    <count date="20080826T00:00:00">0</count>
    <count date="20080827T00:00:00">0</count>
    <count date="20080828T00:00:00">0</count>
    <count date="20080829T00:00:00">0</count>
    <count date="20080830T00:00:00">0</count>
    <count date="20080831T00:00:00">0</count>
    <count date="20080901T00:00:00">0</count>
    <count date="20080902T00:00:00">0</count>
    <count date="20080903T00:00:00">0</count>
    <count date="20080904T00:00:00">0</count>
    <count date="20080905T00:00:00">0</count>
    <count date="20080906T00:00:00">0</count>
    <count date="20080907T00:00:00">0</count>
    <count date="20080908T00:00:00">0</count>
    <count date="20080909T00:00:00">0</count>
    <count date="20080910T00:00:00">0</count>
    <count date="20080911T00:00:00">0</count>
    <count date="20080912T00:00:00">0</count>
    <count date="20080913T00:00:00">0</count>
    <count date="20080914T00:00:00">0</count>
    <count date="20080915T00:00:00">0</count>
    <count date="20080916T00:00:00">0</count>
    <count date="20080917T00:00:00">0</count>
    <count date="20080918T00:00:00">0</count>
    <count date="20080919T00:00:00">0</count>
    <count date="20080920T00:00:00">0</count>
    <count date="20080921T00:00:00">0</count>
    <count date="20080922T00:00:00">0</count>
    <count date="20080923T00:00:00">1</count>
  </daily_counts>
</rsp>
